AUTHOR
LICENSE
MANIFEST.in
README.rst
setup.py
stackups.py
stackups.egg-info/PKG-INFO
stackups.egg-info/SOURCES.txt
stackups.egg-info/dependency_links.txt
stackups.egg-info/requires.txt
stackups.egg-info/top_level.txt