Metadata-Version: 1.1
Name: stackups
Version: 1.2.5
Summary: Stack up analyis: calculate clearances between machinery parts.
Home-page: http://www.newconceptzdesign.com/
Author: Kenneth E. Carlton
Author-email: kencarlton777@gmail.com
License: BSD
Keywords: stackups stackup engineering mechanical engineer machinery machine tolerance design designer clearance six sigma
Platform: any
Classifier: Development Status :: 3 - Alpha
Classifier: Programming Language :: Python
Classifier: Environment :: Console
Classifier: Intended Audience :: Manufacturing
Classifier: Natural Language :: English
Classifier: Operating System :: OS Independent
Classifier: Topic :: Scientific/Engineering
Classifier: License :: OSI Approved :: BSD License
